{
    "AX": {
        "error": 0.02870316177795178, 
        "fit": "average", 
        "value": -0.10436338437249232
    }, 
    "H1": {
        "error": 0.016138094965643796, 
        "fit": "average", 
        "value": 0.0355067447371881
    }, 
    "H2": {
        "error": 0.01208424866172673, 
        "fit": "average", 
        "value": -0.163109539420892
    }, 
    "L1": {
        "error": 0.014653401360947952, 
        "fit": "average", 
        "value": -0.023425944946427878
    }, 
    "L2(CDD)": {
        "error": 9.991314219446925e-06, 
        "fit": "average", 
        "value": 4.4723189007846455e-05
    }
}