{
    "AX": {
        "error": 0.03218703750376129, 
        "fit": "average", 
        "value": -0.0649750991010123
    }, 
    "H1": {
        "error": 0.01726185481749838, 
        "fit": "average", 
        "value": 0.059563245912608635
    }, 
    "H2": {
        "error": 0.012098056150028107, 
        "fit": "average", 
        "value": -0.14116363310227692
    }, 
    "L1": {
        "error": 0.014949974170888176, 
        "fit": "average", 
        "value": -0.017328111223278632
    }, 
    "L2(CDD)": {
        "error": 7.337771407980726e-06, 
        "fit": "average", 
        "value": 2.3676982362789003e-05
    }
}