{
    "AX": {
        "error": 0.005442717955198431, 
        "fit": "average", 
        "value": 0.056269850857350416
    }, 
    "CDD": {
        "error": 1.761777177608971e-06, 
        "fit": "average", 
        "value": 2.5020642325403833e-06
    }, 
    "H1": {
        "error": 0.003986679079498766, 
        "fit": "average", 
        "value": -0.030131394200116283
    }, 
    "H2": {
        "error": 0.004773141060403728, 
        "fit": "average", 
        "value": 0.07469080781013632
    }, 
    "L1": {
        "error": 0.004490175337177394, 
        "fit": "average", 
        "value": 0.14618367817921524
    }, 
    "L2": {
        "error": 0.0023529388400767817, 
        "fit": "average", 
        "value": -0.05736060382746731
    }
}